{
  "message": "Success",
  "payload": [
    {
      "crewId": 352,
      "id": 709,
      "image": "http://place-hoff.com/300/400",
      "name": "Max",
      "userId": 644
    },
    {
      "crewId": 352,
      "id": 713,
      "image": "http://place-hoff.com/300/400",
      "name": "Ines",
      "userId": 649
    },
    {
      "crewId": 352,
      "id": 2245,
      "image": "http://place-hoff.com/300/400",
      "name": "Monika",
      "userId": 2290
    },
    {
      "crewId": 352,
      "id": 2650,
      "image": "http://place-hoff.com/300/400",
      "name": "Mike",
      "userId": 2664
    },
    {
      "crewId": 352,
      "id": 2778,
      "image": "http://place-hoff.com/300/400",
      "name": "Bernhard",
      "userId": 2796
    },
    {
      "crewId": 352,
      "id": 2950,
      "image": "http://place-hoff.com/300/400",
      "name": "Manuel",
      "userId": 2735
    },
    {
      "crewId": 352,
      "id": 5876,
      "image": "http://place-hoff.com/300/400",
      "name": "Daniel",
      "userId": 5293
    },
    {
      "crewId": 352,
      "id": 7111,
      "image": "http://place-hoff.com/300/400",
      "name": "Sandra",
      "userId": 5192
    },
    {
      "crewId": 352,
      "id": 8442,
      "image": "http://place-hoff.com/300/400",
      "name": "Linda",
      "userId": 8007
    },
    {
      "crewId": 352,
      "id": 9364,
      "image": "http://place-hoff.com/300/400",
      "name": "Marlene",
      "userId": 8447
    }
  ]
}
